LICENSE
MANIFEST.in
README.md
setup.py
pyaltt2/__init__.py
pyaltt2/app.py
pyaltt2/config.py
pyaltt2/console.py
pyaltt2/converters.py
pyaltt2/crypto.py
pyaltt2/db.py
pyaltt2/json.py
pyaltt2/locker.py
pyaltt2/logs.py
pyaltt2/lp.py
pyaltt2/mail.py
pyaltt2/network.py
pyaltt2/res.py
pyaltt2.egg-info/PKG-INFO
pyaltt2.egg-info/SOURCES.txt
pyaltt2.egg-info/dependency_links.txt
pyaltt2.egg-info/top_level.txt
pyaltt2/resources/sql/kv.cleanup.sql
pyaltt2/resources/sql/kv.delete.sql
pyaltt2/resources/sql/kv.get.sql
pyaltt2/resources/sql/kv.put.expires.sql
pyaltt2/resources/sql/kv.put.sql