Metadata-Version: 2.1
Name: pyaltt2
Version: 0.0.117
Summary: Misc tools
Home-page: https://github.com/alttch/pyaltt2
Author: Altertech
Author-email: div@altertech.com
License: MIT
Platform: UNKNOWN
Classifier: Programming Language :: Python :: 3
Classifier: License :: OSI Approved :: MIT License
Classifier: Topic :: Software Development :: Libraries
License-File: LICENSE
